fileagent/__init__.py
fileagent/__main__.py
fileagent/all_included.py
fileagent/main.py
fileagent/managers/__init__.py
fileagent/managers/manager_api.py
fileagent/managers/manager_arguments.py
fileagent/managers/manager_files.py
fileagent/managers/manager_snort.py
fileagent-0.2.8.dist-info/licenses/LICENSE
fileagent-0.2.8.dist-info/METADATA
fileagent-0.2.8.dist-info/WHEEL
fileagent-0.2.8.dist-info/entry_points.txt
fileagent-0.2.8.dist-info/top_level.txt
fileagent-0.2.8.dist-info/RECORD
