Metadata-Version: 2.4
Name: fileagent
Version: 0.2.8
Summary: Python fileagent to accompany Snort in a container
Author: Nikolas Filippatos
License: MIT License
Project-URL: Homepage, https://github.com/ISSG-UPAT/FileAgent-SAND5G
Keywords: fileagent,api
Requires-Python: >=3.11
License-File: LICENSE
Requires-Dist: setuptools>=67.7.0
Requires-Dist: wheel>=0.37.0
Requires-Dist: fastapi>=0.110.0
Requires-Dist: uvicorn>=0.34.0
Requires-Dist: requests>=2.30.0
Requires-Dist: python-multipart>=0.0.20
Provides-Extra: dev
Requires-Dist: pytest>=6.2.4; extra == "dev"
Requires-Dist: twine>=3.4.2; extra == "dev"
Requires-Dist: pipdeptree>=2.0.0; extra == "dev"
Requires-Dist: httpx>0.24.0; extra == "dev"
Provides-Extra: docs
Requires-Dist: pdoc3>=0.11.4; extra == "docs"
Dynamic: license-file
